[
  {
    "listing": "/log.html",
    "items": [
      "/posts/Poems/poems-and-thoughts.html",
      "/posts/Resume/resume.html",
      "/posts/Education/index.html",
      "/posts/Evolution/index.html",
      "/posts/Information/index.html"
    ]
  },
  {
    "listing": "/index.html",
    "items": [
      "/posts/Evolution/index.html",
      "/posts/Information/index.html",
      "/posts/Education/index.html",
      "/posts/Poems/poems-and-thoughts.html",
      "/posts/Resume/resume.html",
      "/log.html",
      "/open-notes.html"
    ]
  },
  {
    "listing": "/open-notes.html",
    "items": [
      "/posts/Evolution/index.html",
      "/posts/Information/index.html",
      "/posts/Education/index.html",
      "/posts/Poems/poems-and-thoughts.html",
      "/posts/Resume/resume.html",
      "/log.html",
      "/index.html"
    ]
  }
]